Workbook

Sheet Raw_Data
A1: Order ID | B1: Date | C1: Region | D1: State | E1: Sales Rep | F1: Product Category | G1: Product | H1: Units Sold | I1: Revenue | J1: Profit | K1: Discount (%) | L1: Shipping Cost | M1: Sales Channel | N1: Month | O1: Quarter | P1: Year | Q1: Profit Margin% | R1: Revenue Target
A2: NG-10001 | B2: 45306 | C2: South | D2: Rivers | E2: Amara Okafor | F2: Electronics | G2: Smartphone | H2: 12 | I2: 1250000 | J2: 250000 | K2: 5 | L2: 25000 | M2: Online | N2: =TEXT(tblSales[[#This Row],[Date]],"mmmm") -> January | O2: ="Q"&ROUNDUP(MONTH(tblSales[[#This Row],[Date]])/3,0) -> Q1 | P2: =YEAR(tblSales[[#This Row],[Date]]) -> 2024 | Q2: =tblSales[[#This Row],[Profit]]/tblSales[[#This Row],[Revenue]] -> 0.2 | R2: =tblSales[[#This Row],[Revenue]]*1.1 -> 1375000
A3: NG-10002 | B3: 45307 | C3: West | D3: Lagos | E3: Chidi Okonkwo | F3: Clothing | G3: Denim Jeans | H3: 45 | I3: 675000 | J3: 135000 | K3: 0 | L3: 15000 | M3: Retail | N3: =TEXT(tblSales[[#This Row],[Date]],"mmmm") -> January | O3: ="Q"&ROUNDUP(MONTH(tblSales[[#This Row],[Date]])/3,0) -> Q1 | P3: =YEAR(tblSales[[#This Row],[Date]]) -> 2024 | Q3: =tblSales[[#This Row],[Profit]]/tblSales[[#This Row],[Revenue]] -> 0.2 | R3: =tblSales[[#This Row],[Revenue]]*1.1 -> 742500
A4: NG-10003 | B4: 45307 | C4: North | D4: Kano | E4: Fatima Bello | F4: Food | G4: Rice (5kg) | H4: 200 | I4: 2000000 | J4: 400000 | K4: 0 | L4: 50000 | M4: Wholesale | N4: =TEXT(tblSales[[#This Row],[Date]],"mmmm") -> January | O4: ="Q"&ROUNDUP(MONTH(tblSales[[#This Row],[Date]])/3,0) -> Q1 | P4: =YEAR(tblSales[[#This Row],[Date]]) -> 2024 | Q4: =tblSales[[#This Row],[Profit]]/tblSales[[#This Row],[Revenue]] -> 0.2 | R4: =tblSales[[#This Row],[Revenue]]*1.1 -> 2200000
A5: NG-10004 | B5: 45308 | C5: East | D5: Enugu | E5: Emeka Nwosu | F5: Furniture | G5: Office Chair | H5: 8 | I5: 800000 | J5: 160000 | K5: 10 | L5: 30000 | M5: Online | N5: =TEXT(tblSales[[#This Row],[Date]],"mmmm") -> January | O5: ="Q"&ROUNDUP(MONTH(tblSales[[#This Row],[Date]])/3,0) -> Q1 | P5: =YEAR(tblSales[[#This Row],[Date]]) -> 2024 | Q5: =tblSales[[#This Row],[Profit]]/tblSales[[#This Row],[Revenue]] -> 0.2 | R5: =tblSales[[#This Row],[Revenue]]*1.1 -> 880000
A6: NG-10005 | B6: 45308 | C6: West | D6: Oyo | E6: Oluwaseun Adeyemi | F6: Electronics | G6: Laptop | H6: 5 | I6: 2500000 | J6: 375000 | K6: 15 | L6: 40000 | M6: Online | N6: =TEXT(tblSales[[#This Row],[Date]],"mmmm") -> January | O6: ="Q"&ROUNDUP(MONTH(tblSales[[#This Row],[Date]])/3,0) -> Q1 | P6: =YEAR(tblSales[[#This Row],[Date]]) -> 2024 | Q6: =tblSales[[#This Row],[Profit]]/tblSales[[#This Row],[Revenue]] -> 0.15 | R6: =tblSales[[#This Row],[Revenue]]*1.1 -> 2750000
A7: NG-10006 | B7: 45309 | C7: South | D7: Delta | E7: Ngozi Eze | F7: Clothing | G7: Sneakers | H7: 30 | I7: 900000 | J7: 180000 | K7: 0 | L7: 20000 | M7: Retail | N7: =TEXT(tblSales[[#This Row],[Date]],"mmmm") -> January | O7: ="Q"&ROUNDUP(MONTH(tblSales[[#This Row],[Date]])/3,0) -> Q1 | P7: =YEAR(tblSales[[#This Row],[Date]]) -> 2024 | Q7: =tblSales[[#This Row],[Profit]]/tblSales[[#This Row],[Revenue]] -> 0.2 | R7: =tblSales[[#This Row],[Revenue]]*1.1 -> 990000
A8: NG-10007 | B8: 45310 | C8: North | D8: Kaduna | E8: Ibrahim Musa | F8: Food | G8: Vegetable Oil (5L) | H8: 150 | I8: 1875000 | J8: 375000 | K8: 0 | L8: 60000 | M8: Wholesale | N8: =TEXT(tblSales[[#This Row],[Date]],"mmmm") -> January | O8: ="Q"&ROUNDUP(MONTH(tblSales[[#This Row],[Date]])/3,0) -> Q1 | P8: =YEAR(tblSales[[#This Row],[Date]]) -> 2024 | Q8: =tblSales[[#This Row],[Profit]]/tblSales[[#This Row],[Revenue]] -> 0.2 | R8: =tblSales[[#This Row],[Revenue]]*1.1 -> 2062500
A9: NG-10008 | B9: 45310 | C9: West | D9: Lagos | E9: Tunde Bakare | F9: Electronics | G9: Headphones | H9: 50 | I9: 750000 | J9: 150000 | K9: 5 | L9: 10000 | M9: Online | N9: =TEXT(tblSales[[#This Row],[Date]],"mmmm") -> January | O9: ="Q"&ROUNDUP(MONTH(tblSales[[#This Row],[Date]])/3,0) -> Q1 | P9: =YEAR(tblSales[[#This Row],[Date]]) -> 2024 | Q9: =tblSales[[#This Row],[Profit]]/tblSales[[#This Row],[Revenue]] -> 0.2 | R9: =tblSales[[#This Row],[Revenue]]*1.1 -> 825000
A10: NG-10009 | B10: 45311 | C10: East | D10: Anambra | E10: Ifeanyi Obi | F10: Furniture | G10: Dining Table | H10: 4 | I10: 600000 | J10: 90000 | K10: 20 | L10: 45000 | M10: Retail | N10: =TEXT(tblSales[[#This Row],[Date]],"mmmm") -> January | O10: ="Q"&ROUNDUP(MONTH(tblSales[[#This Row],[Date]])/3,0) -> Q1 | P10: =YEAR(tblSales[[#This Row],[Date]]) -> 2024 | Q10: =tblSales[[#This Row],[Profit]]/tblSales[[#This Row],[Revenue]] -> 0.15 | R10: =tblSales[[#This Row],[Revenue]]*1.1 -> 660000
A11: NG-10010 | B11: 45311 | C11: South | D11: Rivers | E11: Ada Obi | F11: Clothing | G11: Traditional Dress | H11: 25 | I11: 625000 | J11: 125000 | K11: 0 | L11: 12000 | M11: Online | N11: =TEXT(tblSales[[#This Row],[Date]],"mmmm") -> January | O11: ="Q"&ROUNDUP(MONTH(tblSales[[#This Row],[Date]])/3,0) -> Q1 | P11: =YEAR(tblSales[[#This Row],[Date]]) -> 2024 | Q11: =tblSales[[#This Row],[Profit]]/tblSales[[#This Row],[Revenue]] -> 0.2 | R11: =tblSales[[#This Row],[Revenue]]*1.1 -> 687500
A12: NG-10011 | B12: 45312 | C12: North | D12: Kano | E12: Aisha Mohammed | F12: Food | G12: Bread Loaf | H12: 300 | I12: 750000 | J12: 150000 | K12: 0 | L12: 40000 | M12: Wholesale | N12: =TEXT(tblSales[[#This Row],[Date]],"mmmm") -> January | O12: ="Q"&ROUNDUP(MONTH(tblSales[[#This Row],[Date]])/3,0) -> Q1 | P12: =YEAR(tblSales[[#This Row],[Date]]) -> 2024 | Q12: =tblSales[[#This Row],[Profit]]/tblSales[[#This Row],[Revenue]] -> 0.2 | R12: =tblSales[[#This Row],[Revenue]]*1.1 -> 825000
A13: NG-10012 | B13: 45313 | C13: West | D13: Ogun | E13: Segun Ogunleye | F13: Electronics | G13: Power Bank | H13: 40 | I13: 400000 | J13: 80000 | K13: 0 | L13: 8000 | M13: Retail | N13: =TEXT(tblSales[[#This Row],[Date]],"mmmm") -> January | O13: ="Q"&ROUNDUP(MONTH(tblSales[[#This Row],[Date]])/3,0) -> Q1 | P13: =YEAR(tblSales[[#This Row],[Date]]) -> 2024 | Q13: =tblSales[[#This Row],[Profit]]/tblSales[[#This Row],[Revenue]] -> 0.2 | R13: =tblSales[[#This Row],[Revenue]]*1.1 -> 440000
... A501: NG-10500 | B501: 45593 | C501: West | D501: Oyo | E501: Teni | F501: Clothing | G501: Hair Turban | H501: 120 | I501: 120000 | J501: 24000 | K501: 0 | L501: 4000 | M501: Retail | N501: =TEXT(tblSales[[#This Row],[Date]],"mmmm") -> October | O501: ="Q"&ROUNDUP(MONTH(tblSales[[#This Row],[Date]])/3,0) -> Q4 | P501: =YEAR(tblSales[[#This Row],[Date]]) -> 2024 | Q501: =tblSales[[#This Row],[Profit]]/tblSales[[#This Row],[Revenue]] -> 0.2 | R501: =tblSales[[#This Row],[Revenue]]*1.1 -> 132000

Sheet Pivot_Tables
A1: Region | B1: Sum of Revenue | D1: Product | E1: Sum of Profit
A2: East | B2: 65797500 | D2: iPhone 15 Pro Max | E2: 18750000
A3: North | B3: 253125000 | D3: MacBook Pro M3 | E3: 10500000
A4: South | B4: 205752500 | D4: Rice (50kg bag) | E4: 10000000
A5: West | B5: 200277500 | D5: Broken Rice (50kg) | E5: 4000000
A6: Grand Total | B6: 724952500 | D6: Garri (Ihutech 50kg) | E6: 3000000
D7: Samsung Galaxy Z Fold 6 | E7: 2700000
A8: Product Category | B8: Sum of Revenue | D8: Cow (whole) | E8: 2700000
A9: Clothing | B9: 81522500 | D9: PS5 Console | E9: 2500000
A10: Electronics | B10: 337802500 | D10: Onions (50kg bag) | E10: 2500000
A11: Food | B11: 255365000 | D11: Gaming Laptop RTX 4090 | E11: 2400000
A12: Furniture | B12: 50262500 | D12: Wedding Aso Ebi (100 pieces) | E12: 1600000
A13: Grand Total | B13: 724952500 | D13: Semovita (50kg bag) | E13: 1600000
D14: Maize (50kg bag) | E14: 1500000
A15: Month | B15: Sum of Revenue | D15: Frozen Chicken (crate) | E15: 1500000
A16: January | B16: 21742500 | D16: Air Conditioner 1.5HP | E16: 1350000
A17: February | B17: 23222500 | D17: Smart TV 65 inch | E17: 1260000
A18: March | B18: 16767500 | D18: Solar Inverter 5KVA | E18: 1125000
A19: April | B19: 11165000 | D19: Vegetable Oil (25L keg) | E19: 1000000
A20: May | B20: 9760000 | D20: School Uniforms (bulk) | E20: 1000000
A21: June | B21: 443845000 | D21: Milk Powder (25kg) | E21: 1000000
A22: July | B22: 140100000 | D22: Sugar (50kg bag) | E22: 900000
A23: August | B23: 36850000 | D23: Generator 2.5KVA | E23: 900000
A24: September | B24: 10195000 | D24: Cooking Gas Cylinder (12.5kg) | E24: 900000
A25: October | B25: 11305000 | D25: Massage Chair | E25: 810000
A26: Grand Total | B26: 724952500 | D26: Wheat Flour (50kg) | E26: 800000
D27: Portable Bluetooth Speaker (JBL) | E27: 800000
D28: Pounded Yam Flour (10kg) | E28: 750000
D29: Executive Leather Sofa | E29: 750000
D30: Peak Milk Tin | E30: 720000
D31: Palm Oil (25L keg) | E31: 720000
D32: Power Bank 50000mAh | E32: 675000
D33: Yam Tuber (per crate) | E33: 625000
D34: Smartwatch Ultra | E34: 600000
D35: Fresh Tomatoes (crate) | E35: 600000
D36: Golden Morn (carton) | E36: 560000
D37: Batakari (Fugu) | E37: 560000
D38: Designer Handbag (Original) | E38: 525000
... D499: Grand Total | E499: 127683125

Sheet KPI_Calculations
A1: KPI Labels
A2: Total Revenue | B2: =SUM(tblSales[Revenue]) -> 724952500
A3: Total Profit | B3: =SUM(tblSales[Profit]) -> 127683125
A4: Units Sold | B4: =SUM(tblSales[Units Sold]) -> 67991
A5: Profit Margin % | B5: =SUM(tblSales[Profit])/SUM(tblSales[Revenue]) -> 0.17612619
A6: Best Product | B6: {=_xlfn.XLOOKUP(MAX(tblSales[Revenue]),tblSales[Revenue],tblSales[Product])} -> iPhone 15 Pro Max
A7: Best Region | B7: {=_xlfn.XLOOKUP(MAX(tblSales[Revenue]),tblSales[Revenue],tblSales[Region])} -> South
A8: Average Order Value | B8: =AVERAGE(tblSales[Revenue]) -> 1449905
A10: Month | B10: Revenue | C10: MoM %
A11: January | B11: {=Pivot_Tables!B16:B25} -> 21742500
A12: February | B12: 23222500 | C12: =(B12-B11)/B11 -> 0.068069449
A13: March | B13: 16767500 | C13: =(B13-B12)/B12 -> -0.27796318
A14: April | B14: 11165000 | C14: =(B14-B13)/B13 -> -0.33412852
A15: May | B15: 9760000 | C15: =(B15-B14)/B14 -> -0.12583968
A16: June | B16: 443845000 | C16: =(B16-B15)/B15 -> 44.475922
A17: July | B17: 140100000 | C17: =(B17-B16)/B16 -> -0.68434927
A18: August | B18: 36850000 | C18: =(B18-B17)/B17 -> -0.73697359
A19: September | B19: 10195000 | C19: =(B19-B18)/B18 -> -0.72333786
A20: October | B20: 11305000 | C20: =(B20-B19)/B19 -> 0.1088769
A22: Current Month Revenue | B22: {=LOOKUP(2,1/(Pivot_Tables!B16:B25<>""),Pivot_Tables!B16:B25)} -> 11305000
A23: Previous Month Revenue | B23: {=INDEX(Pivot_Tables!B16:B25,COUNTA(Pivot_Tables!B16:B25)-1)} -> 10195000
A24: MoM Growth % | B24: {=(LOOKUP(2,1/(Pivot_Tables!B16:B25<>""),Pivot_Tables!B16:B25)-INDEX(Pivot_Tables!B16:B25,COUNTA(Pivot_Tables!B16:B25)-1))/INDEX(Pivot_Tables!B16:B25,COUNTA(Pivot_Tables!B16:B25)-1)} -> 0.1088769
A25: Total Growth % | B25: {=(LOOKUP(2,1/(Pivot_Tables!B16:B25<>""),Pivot_Tables!B16:B25)-INDEX(Pivot_Tables!B16:B25,1))/INDEX(Pivot_Tables!B16:B25,1)} -> -0.48005059

Sheet Dashboard
